odoo/addons/l10n_fi_payment_terms/README.rst
odoo/addons/l10n_fi_payment_terms/__init__.py
odoo/addons/l10n_fi_payment_terms/__manifest__.py
odoo/addons/l10n_fi_payment_terms/data/payment_terms_finnish.xml
odoo/addons/l10n_fi_payment_terms/i18n/fi.po
odoo/addons/l10n_fi_payment_terms/i18n/l10n_fi_payment_terms.pot
odoo/addons/l10n_fi_payment_terms/models/__init__.py
odoo/addons/l10n_fi_payment_terms/models/payment_term.py
odoo/addons/l10n_fi_payment_terms/readme/CONFIGURE.rst
odoo/addons/l10n_fi_payment_terms/readme/CONTRIBUTORS.rst
odoo/addons/l10n_fi_payment_terms/readme/CREDITS.rst
odoo/addons/l10n_fi_payment_terms/readme/DESCRIPTION.rst
odoo/addons/l10n_fi_payment_terms/readme/HISTORY.rst
odoo/addons/l10n_fi_payment_terms/readme/MAINTAINER.rst
odoo/addons/l10n_fi_payment_terms/static/description/icon.png
odoo/addons/l10n_fi_payment_terms/static/description/index.html
odoo14_addon_l10n_fi_payment_terms-14.0.1.0.1.dev5.dist-info/METADATA
odoo14_addon_l10n_fi_payment_terms-14.0.1.0.1.dev5.dist-info/WHEEL
odoo14_addon_l10n_fi_payment_terms-14.0.1.0.1.dev5.dist-info/top_level.txt
odoo14_addon_l10n_fi_payment_terms-14.0.1.0.1.dev5.dist-info/RECORD
